domain_park/__init__.py
domain_park/_version.py
domain_park/cli.py
domain_park/server.py
domain_park-0.4.1.dist-info/LICENCE
domain_park-0.4.1.dist-info/METADATA
domain_park-0.4.1.dist-info/NOTICE
domain_park-0.4.1.dist-info/WHEEL
domain_park-0.4.1.dist-info/entry_points.txt
domain_park-0.4.1.dist-info/top_level.txt
domain_park-0.4.1.dist-info/RECORD
