Metadata-Version: 2.1
Name: domain-park
Version: 0.4.1
Summary: DNS server for parking domains securely
Author-email: Nicholas Hairs <info+domain-park@nicholashairs.com>
License: MIT License
Project-URL: homepage, https://github.com/nhairs/domain-park
Classifier: Programming Language :: Python :: 3 :: Only
Classifier: Programming Language :: Python :: 3.8
Classifier: Programming Language :: Python :: 3.9
Classifier: Programming Language :: Python :: 3.10
Classifier: Programming Language :: Python :: 3.11
Classifier: Development Status :: 3 - Alpha
Classifier: License :: OSI Approved :: MIT License
Classifier: Topic :: Internet
Classifier: Topic :: Internet :: Name Service (DNS)
Requires-Python: >=3.8
License-File: LICENCE
License-File: NOTICE
Requires-Dist: nserver ==1.0.2
Requires-Dist: netifaces
Requires-Dist: pillar[recommended] ==0.3.0
Provides-Extra: dev
Requires-Dist: setuptools ; extra == 'dev'
Requires-Dist: wheel ; extra == 'dev'
Requires-Dist: black ; extra == 'dev'
Requires-Dist: pylint ; extra == 'dev'
Requires-Dist: mypy ; extra == 'dev'
Requires-Dist: pytest ; extra == 'dev'
Requires-Dist: mkdocs ; extra == 'dev'
Requires-Dist: mkdocs-material >=8.5 ; extra == 'dev'
Requires-Dist: mkdocs-awesome-pages-plugin ; extra == 'dev'
Requires-Dist: mdx-truly-sane-lists ; extra == 'dev'
Requires-Dist: bpython ; extra == 'dev'
